{"cameraMode":{"drawMode":0,"name":"Shaded","section":"Shading Mode"},"sceneLighting":false,"audioPlay":false,"sceneViewState":{"showFog":true,"showMaterialUpdate":false,"showSkybox":false,"showFlares":true,"showImageEffects":true,"showParticleSystems":true},"in2DMode":false,"pivot":{"x":-12.100000381469727,"y":5.657247543334961,"z":1.8200907707214356},"rotation":{"x":0.2788245677947998,"y":0.16212600469589234,"z":-0.047865111380815509,"w":0.9453972578048706},"size":27.41600227355957,"orthographic":false}